alertaseism/__init__.py
alertaseism-0.0.5.dist-info/DESCRIPTION.rst
alertaseism-0.0.5.dist-info/METADATA
alertaseism-0.0.5.dist-info/RECORD
alertaseism-0.0.5.dist-info/WHEEL
alertaseism-0.0.5.dist-info/metadata.json
alertaseism-0.0.5.dist-info/top_level.txt
