Metadata-Version: 2.0
Name: alertaseism
Version: 0.0.5
Summary: O librarie folosiind date XML de la INFP pentru a afla magnitudinea la secunda. 
Home-page: https://github.com/TudorGruian/alerta-seism-python3
Author: Tudor Gruian
Author-email: gruiantudor@hotmail.com
License: UNKNOWN
Platform: UNKNOWN
Classifier: Programming Language :: Python :: 3
Classifier: License :: OSI Approved :: MIT License
Classifier: Operating System :: OS Independent
Requires-Dist: beautifulsoup4
Requires-Dist: requests
